telegram_handler/__init__.py
telegram_handler/buffer.py
telegram_handler/consts.py
telegram_handler/errors.py
telegram_handler/handler.py
telegram_handler-1.4.5.dist-info/METADATA
telegram_handler-1.4.5.dist-info/WHEEL
telegram_handler-1.4.5.dist-info/top_level.txt
telegram_handler-1.4.5.dist-info/RECORD
