Metadata-Version: 2.4
Name: telegram-handler
Version: 1.4.5
Summary: Small package for working with config files
Author: Guyshe
Project-URL: Homepage, https://github.com/guyshe/telegram_handler
Classifier: Programming Language :: Python :: 3
Classifier: License :: OSI Approved :: MIT License
Classifier: Operating System :: OS Independent
Requires-Python: >=3
Requires-Dist: requests>=2.25
Requires-Dist: retry>=0.9
